[
  {
    "source": "https://www.strzelce360.pl/rss/articles/pl",
    "link": "https://www.strzelce360.pl/artykul/11253,czolowe-zderzenie-pod-strzelcami-opolskimi-jedna-osoba-poszkodowana",
    "title": "Czołowe zderzenie pod Strzelcami Opolskimi. Jedna osoba poszkodowana",
    "summary": "Do zdarzenia doszło we wtorek, 24 lutego, po godz. 16.00 na drodze krajowej nr 94 między Strzelcami Opolskimi a Suchą. Zderzyły się dwa samochody osobowe.",
    "content": "Do zdarzenia doszło we wtorek, 24 lutego, po godz. 16.00 na drodze krajowej nr 94 między Strzelcami Opolskimi a Suchą. Zderzyły się dwa samochody osobowe.",
    "published": "2026-02-24T17:04:00+01:00",
    "id": "fa69a94db157aa7cd5ba9f1e5aceba54df6d9980",
    "preselect": true,
    "places_german": [
      "Gross Strehlitz",
      "Sucha"
    ]
  }
]