[
  {
    "source": "https://wild-union-5400.thedatasculptor.workers.dev/",
    "link": "https://strzelceopolskie.naszemiasto.pl/wyniki-lotto-z-21-05-2026-lista-kolektur-w-ujezdzie/ar/c1p1-27025429",
    "title": "Wyniki Lotto z 21.05.2026. Lista kolektur w Ujeździe",
    "summary": "",
    "content": "",
    "published": "2026-05-22T02:58:57+00:00",
    "id": "d59a7430821bfc200ef9f7e57b7d1fdcfbf43dec",
    "preselect": false
  },
  {
    "source": "https://wild-union-5400.thedatasculptor.workers.dev/",
    "link": "https://strzelceopolskie.naszemiasto.pl/wyniki-lotto-z-21-05-2026-sprawdz-liste-kolektur-w-lesnicy/ar/c1p1-27025203",
    "title": "Wyniki Lotto z 21.05.2026. Sprawdź listę kolektur w Leśnicy",
    "summary": "",
    "content": "",
    "published": "2026-05-22T02:58:57+00:00",
    "id": "3daab969e4ff80ec4ad4b3a8681c0628598970f6",
    "preselect": false
  },
  {
    "source": "https://wild-union-5400.thedatasculptor.workers.dev/",
    "link": "https://strzelceopolskie.naszemiasto.pl/zobacz-liste-kolektur-w-kolonowskiem-i-wyniki-lotto-z-21-05-2026/ar/c1p1-27025037",
    "title": "Zobacz listę kolektur w Kolonowskiem i wyniki Lotto z 21.05.2026",
    "summary": "",
    "content": "",
    "published": "2026-05-22T02:58:57+00:00",
    "id": "e25cc810c8eb168f8eaacb6a500886e0b05417c3",
    "preselect": false
  },
  {
    "source": "https://wild-union-5400.thedatasculptor.workers.dev/",
    "link": "https://strzelceopolskie.naszemiasto.pl/wyniki-lotto-z-21-05-2026-zobacz-liste-kolektur-w-zawadzkiem/ar/c1p1-27024533",
    "title": "Wyniki lotto z 21.05.2026. Zobacz listę kolektur w Zawadzkiem",
    "summary": "",
    "content": "",
    "published": "2026-05-22T02:58:57+00:00",
    "id": "2a204b85bf751724eb94420868cd3d70a300d19e",
    "preselect": false
  },
  {
    "source": "https://wild-union-5400.thedatasculptor.workers.dev/",
    "link": "https://strzelceopolskie.naszemiasto.pl/wyniki-lotto-z-21-05-2026-sprawdz-liste-kolektur-w-strzelcach-opolskich/ar/c1p1-27024037",
    "title": "Wyniki Lotto z 21.05.2026. Sprawdź listę kolektur w Strzelcach Opolskich",
    "summary": "",
    "content": "",
    "published": "2026-05-22T02:58:57+00:00",
    "id": "b735a382f1ab4643b35111eb9bf382a4fecb4183",
    "preselect": true
  },
  {
    "source": "https://wild-union-5400.thedatasculptor.workers.dev/",
    "link": "https://strzelceopolskie.naszemiasto.pl/utrudnienia-w-ruchu-woj-opolskie-gdzie-trwaja-roboty-drogowe-sprawdz-stan-na-21-05-2026/ar/c1p1-21631769",
    "title": "Utrudnienia w ruchu: woj. opolskie. Gdzie trwają roboty drogowe? Sprawdź stan na 21.05.2026",
    "summary": "",
    "content": "",
    "published": "2026-05-22T02:58:57+00:00"
  },
  {
    "source": "https://wild-union-5400.thedatasculptor.workers.dev/",
    "link": "https://strzelceopolskie.naszemiasto.pl/pomnik-na-gorze-swietej-anny-doczeka-sie-remontu-w-koncu-zapadly-konkretne-decyzje/ar/c1p2-29019629",
    "title": "Pomnik na Górze Świętej Anny doczeka się remontu. W końcu zapadły konkretne decyzje",
    "summary": "",
    "content": "",
    "published": "2026-05-22T02:58:57+00:00",
    "id": "c8096108d4aa500d7a18f441b722ea6d7f272cff",
    "preselect": false
  },
  {
    "source": "https://wild-union-5400.thedatasculptor.workers.dev/",
    "link": "https://motofakty.pl/ceny-samochodow-uzywanych-w-ktorych-wojewodztwach-jest-najtaniej-a-w-ktorych-najdrozej/ar/c4p2-29016007",
    "title": "Ceny samochodów używanych. W których województwach jest najtaniej, a w których najdrożej?",
    "summary": "",
    "content": "",
    "published": "2026-05-22T02:58:57+00:00",
    "id": "1803419e53bf07f711f3a7b3c9ebfb55f5ccc8e5",
    "preselect": false
  },
  {
    "source": "https://wild-union-5400.thedatasculptor.workers.dev/",
    "link": "https://strzelceopolskie.naszemiasto.pl/tak-wygladala-mechanizacja-naszego-rolnictwa-konie-traktory/ar/c1-8810341",
    "title": "Tak wyglądała mechanizacja naszego rolnictwa. Konie, traktory, kombajny i samoloty",
    "summary": "",
    "content": "",
    "published": "2026-05-22T02:58:57+00:00",
    "id": "b43579918a3f91e729a3bb65e1330af6036a2d38",
    "preselect": false
  },
  {
    "source": "https://wild-union-5400.thedatasculptor.workers.dev/",
    "link": "https://strzelceopolskie.naszemiasto.pl/przejedzie-polske-rowerem-na-zywo-latwogang-rzuca-kolejne-wyzwanie-i-tym-razem-walczy-o-zycie-8-latka/ar/c13p2-29019395",
    "title": "Przejedzie Polskę rowerem na żywo. Łatwogang rzuca kolejne wyzwanie i tym razem walczy o życie 8-latka!",
    "summary": "",
    "content": "",
    "published": "2026-05-22T02:58:57+00:00",
    "id": "9be1f978387a24bd2a10fc949acf6c75037bd4f2",
    "preselect": false
  },
  {
    "source": "https://wild-union-5400.thedatasculptor.workers.dev/",
    "link": "https://motofakty.pl/komunikat-dla-kierowcow-ministerstwo-podalo-nowe-stawki/ar/c4p2-29018143",
    "title": "Komunikat dla kierowców. Ministerstwo podało nowe stawki",
    "summary": "",
    "content": "",
    "published": "2026-05-22T02:58:57+00:00",
    "id": "e644d8f1fd1e57a63ed19a426bb60f19cbb67093",
    "preselect": false
  },
  {
    "source": "https://wild-union-5400.thedatasculptor.workers.dev/",
    "link": "https://strzelceopolskie.naszemiasto.pl/pijacka-awantura-i-trzylatek-w-srodku-domowego-piekla-trzy-promile-u-ojca-poltora-u-matki/ar/c1p2-29018735",
    "title": "Pijacka awantura i trzylatek w środku domowego piekła. Trzy promile u ojca, półtora u matki",
    "summary": "",
    "content": "",
    "published": "2026-05-22T02:58:57+00:00",
    "id": "db7ca8f206551e208406d146da1ad4cf05682ace",
    "preselect": false
  },
  {
    "source": "https://wild-union-5400.thedatasculptor.workers.dev/",
    "link": "https://strzelceopolskie.naszemiasto.pl/ponad-500-przydomowych-oczyszczalni-sciekow-powstanie-na-opolszczyznie-bedzie-kolejny-nabor/ar/c1p2-29013175",
    "title": "Ponad 500 przydomowych oczyszczalni ścieków powstanie na Opolszczyźnie. Będzie kolejny nabór",
    "summary": "",
    "content": "",
    "published": "2026-05-22T02:58:57+00:00"
  },
  {
    "source": "https://wild-union-5400.thedatasculptor.workers.dev/",
    "link": "https://strzelceopolskie.naszemiasto.pl/promocje-na-ubrania-czwartek-21-05-2026-reserved-mohito-house-i-cropp-czy-uda-ci-sie-cos-wybrac/ar/c15p1-20976483",
    "title": "Promocje na ubrania czwartek, 21.05.2026 - Reserved, Mohito, House i Cropp. Czy uda Ci się coś wybrać? 1",
    "summary": "",
    "content": "",
    "published": "2026-05-22T02:58:57+00:00",
    "id": "e4178df6a5f542dcbf7de480681766779ed25089",
    "preselect": false
  },
  {
    "source": "https://wild-union-5400.thedatasculptor.workers.dev/",
    "link": "https://strzelceopolskie.naszemiasto.pl/promocje-na-sprzet-w-elektromarketach-na-czwartek-21-05-2026-co-uda-ci-sie-kupic-taniej/ar/c15p1-20917240",
    "title": "Promocje na sprzęt w elektromarketach na czwartek, 21.05.2026. Co uda Ci się kupić taniej? 8",
    "summary": "",
    "content": "",
    "published": "2026-05-22T02:58:57+00:00",
    "id": "a906f176bf26f5f48419b4dad5066f8c3b7a684a",
    "preselect": false
  }
]