[
  {
    "source": "https://wild-union-5400.thedatasculptor.workers.dev/",
    "link": "https://strzelceopolskie.naszemiasto.pl/wyniki-lotto-z-2-05-2026-zobacz-liste-kolektur-w-ujezdzie/ar/c1p1-27025429",
    "title": "Wyniki lotto z 2.05.2026. Zobacz listę kolektur w Ujeździe",
    "summary": "",
    "content": "",
    "published": "2026-05-02T15:42:23+00:00",
    "id": "b006a63d0758c93004fbd1974650b08cafdd9c8a",
    "preselect": false
  },
  {
    "source": "https://wild-union-5400.thedatasculptor.workers.dev/",
    "link": "https://strzelceopolskie.naszemiasto.pl/wyniki-lotto-z-2-05-2026-i-kolektury-w-lesnicy-sprawdz-lokalizacje/ar/c1p1-27025203",
    "title": "Wyniki Lotto z 2.05.2026 i kolektury w Leśnicy: sprawdź lokalizacje",
    "summary": "",
    "content": "",
    "published": "2026-05-02T15:42:23+00:00",
    "id": "8b394798f16530d74e7a6f6e2a7098b6a827b6ab",
    "preselect": false
  },
  {
    "source": "https://wild-union-5400.thedatasculptor.workers.dev/",
    "link": "https://strzelceopolskie.naszemiasto.pl/wyniki-lotto-z-2-05-2026-sprawdz-kolektury-w-kolonowskiem/ar/c1p1-27025037",
    "title": "Wyniki Lotto z 2.05.2026 – sprawdź kolektury w Kolonowskiem",
    "summary": "",
    "content": "",
    "published": "2026-05-02T15:42:23+00:00",
    "id": "20dee1499ccec4af7ce50cd73222dff753082b50",
    "preselect": false
  },
  {
    "source": "https://wild-union-5400.thedatasculptor.workers.dev/",
    "link": "https://strzelceopolskie.naszemiasto.pl/wyniki-lotto-z-2-05-2026-zobacz-liste-kolektur-w-zawadzkiem/ar/c1p1-27024533",
    "title": "Wyniki lotto z 2.05.2026. Zobacz listę kolektur w Zawadzkiem",
    "summary": "",
    "content": "",
    "published": "2026-05-02T15:42:23+00:00",
    "id": "8984dc22fc537d15c74b78f624a4efff9235b982",
    "preselect": false
  },
  {
    "source": "https://wild-union-5400.thedatasculptor.workers.dev/",
    "link": "https://strzelceopolskie.naszemiasto.pl/zobacz-liste-kolektur-w-strzelcach-opolskich-i-wyniki-lotto-z-2-05-2026/ar/c1p1-27024037",
    "title": "Zobacz listę kolektur w Strzelcach Opolskich i wyniki Lotto z 2.05.2026",
    "summary": "",
    "content": "",
    "published": "2026-05-02T15:42:23+00:00",
    "id": "c2bd76dfe484da1e7086f45ec7f17a886a962323",
    "preselect": true
  },
  {
    "source": "https://wild-union-5400.thedatasculptor.workers.dev/",
    "link": "https://strzelceopolskie.naszemiasto.pl/ubrania-a-nizszych-cenach-w-sklepach-sieci-reserved-house-cropp-i-mohito-w-sobote-2-05-2026-sprawdz-co-jest-w-promocji/ar/c15p1-20976483",
    "title": "Ubrania a niższych cenach w sklepach sieci Reserved, House, Cropp i Mohito w sobotę, 2.05.2026. Sprawdź, co jest w promocji 1",
    "summary": "",
    "content": "",
    "published": "2026-05-02T15:42:23+00:00",
    "id": "373419eb6646bdccf062ebae8979add9deea279a",
    "preselect": false
  },
  {
    "source": "https://wild-union-5400.thedatasculptor.workers.dev/",
    "link": "https://strzelceopolskie.naszemiasto.pl/szukasz-sprzetu-w-elektromarketach-zobacz-jakie-promocje-udalo-nam-sie-znalezc-na-sobote-2-05-2026/ar/c15p1-20917240",
    "title": "Szukasz sprzętu w elektromarketach? Zobacz, jakie promocje udało nam się znaleźć na sobotę, 2.05.2026 8",
    "summary": "",
    "content": "",
    "published": "2026-05-02T15:42:23+00:00",
    "id": "4f4bf45efb2adda3ded12d1168b895e2962440de",
    "preselect": false
  },
  {
    "source": "https://wild-union-5400.thedatasculptor.workers.dev/",
    "link": "https://strzelceopolskie.naszemiasto.pl/wniebowstapienie-panskie-2026-msze-swiete-online-informacje-o-transmisjach/ar/c15p1-24838941",
    "title": "Wniebowstąpienie Pańskie 2026 - msze święte online. Informacje o transmisjach",
    "summary": "",
    "content": "",
    "published": "2026-05-02T15:42:23+00:00",
    "id": "e086a83d1a467e066a75fa6ba0f3656ae5cb3684",
    "preselect": false
  },
  {
    "source": "https://wild-union-5400.thedatasculptor.workers.dev/",
    "link": "https://strzelceopolskie.naszemiasto.pl/prasowka-ze-strzelec-opolskich-2-05-2026-przeglad-prasy-zestawienie-najwazniejszych-informacji/ar/c1p1-19739151",
    "title": "Prasówka ze Strzelec Opolskich 2.05.2026. Przegląd prasy - zestawienie najważniejszych informacji",
    "summary": "",
    "content": "",
    "published": "2026-05-02T15:42:23+00:00"
  },
  {
    "source": "https://wild-union-5400.thedatasculptor.workers.dev/",
    "link": "https://strzelceopolskie.naszemiasto.pl/msze-swiete-w-telewizji-i-online-sobota-2-05-2026-gdzie-ogladac-msze-swiete-godziny-i-informacje-o-transmisjach/ar/c15p1-21253041",
    "title": "Msze święte w telewizji i online. Sobota, 2.05.2026. Gdzie oglądać msze święte? Godziny i informacje o transmisjach",
    "summary": "",
    "content": "",
    "published": "2026-05-02T15:42:23+00:00",
    "id": "706e84a3455dcffffda289ff6eb7347b7821afdc",
    "preselect": false
  },
  {
    "source": "https://wild-union-5400.thedatasculptor.workers.dev/",
    "link": "https://strzelceopolskie.naszemiasto.pl/xiii-jarmark-cysterski-w-jemielnicy-tutaj-bawia-sie-cale-rodziny/ar/c1p2-28961779",
    "title": "XIII Jarmark Cysterski w Jemielnicy. Tutaj bawią się całe rodziny",
    "summary": "",
    "content": "",
    "published": "2026-05-02T15:42:23+00:00",
    "id": "a3977f037765ca35c90238d4b8d0c5928328cde5",
    "preselect": false
  },
  {
    "source": "https://wild-union-5400.thedatasculptor.workers.dev/",
    "link": "https://strzelceopolskie.naszemiasto.pl/prasowka-z-kwietnia-2026-sprawdz-co-dzialo-sie-w-strzelcach-opolskich-czy-jestes-na-biezaco/ar/c1p1-28962217",
    "title": "Prasówka z kwietnia 2026. Sprawdź, co działo się w Strzelcach Opolskich. Czy jesteś na bieżąco?",
    "summary": "",
    "content": "",
    "published": "2026-05-02T15:42:23+00:00"
  },
  {
    "source": "https://wild-union-5400.thedatasculptor.workers.dev/",
    "link": "https://strzelceopolskie.naszemiasto.pl/jarmark-cysterski-i-diecezjalne-swieto-rodziny-w-jemielnicy-atrakcje-potrwaja-do-wieczora/ar/c1p2-28961363",
    "title": "Jarmark Cysterski i Diecezjalne Święto Rodziny w Jemielnicy. Atrakcje potrwają do wieczora",
    "summary": "",
    "content": "",
    "published": "2026-05-02T15:42:23+00:00",
    "id": "e3754d56f21f7e5556851063d308c3988da4df9e",
    "preselect": false
  },
  {
    "source": "https://wild-union-5400.thedatasculptor.workers.dev/",
    "link": "https://strzelceopolskie.naszemiasto.pl/to-moze-byc-dobra-okazja-oto-najtansze-domy-na-sprzedaz-w-regionie/ar/c1p2-28808447",
    "title": "To może być dobra okazja. Oto najtańsze domy na sprzedaż w regionie",
    "summary": "",
    "content": "",
    "published": "2026-05-02T15:42:23+00:00",
    "id": "b0e3fc42f9dfdc09d930c3b0f0371243b2ad7911",
    "preselect": false
  },
  {
    "source": "https://wild-union-5400.thedatasculptor.workers.dev/",
    "link": "https://strzelceopolskie.naszemiasto.pl/google-wybral-10-najlepszych-atrakcji-opolszczyzny-niektore/ar/c1-9598267",
    "title": "Google wybrał 10 najlepszych atrakcji Opolszczyzny. Niektóre są dużym zaskoczeniem",
    "summary": "",
    "content": "",
    "published": "2026-05-02T15:42:23+00:00"
  }
]