[
  {
    "source": "https://wild-union-5400.thedatasculptor.workers.dev/",
    "link": "https://strzelceopolskie.naszemiasto.pl/utrudnienia-w-ruchu-w-woj-opolskim-5-05-2026-lista-aktualnych-remontow-drog-i-innych-zdarzen/ar/c1p1-21631769",
    "title": "Utrudnienia w ruchu w woj. opolskim 5.05.2026. Lista aktualnych remontów dróg i innych zdarzeń",
    "summary": "",
    "content": "",
    "published": "2026-05-05T10:43:41+00:00",
    "id": "712984254656df54dea39619907bacad1c449f84",
    "preselect": true,
    "places_german": [
      "Oppeln"
    ]
  }
]