[
  {
    "source": "https://www.strzelce360.pl/rss/articles/pl",
    "link": "https://www.strzelce360.pl/artykul/10686,zuzyte-oleje-i-smary-jak-firmy-powinny-je-utylizowac-zgodnie-z-przepisami",
    "title": "Zużyte oleje i smary - jak firmy powinny je utylizować zgodnie z przepisami?",
    "summary": "Zużyte oleje i smary to odpady niebezpieczne dla ludzi i środowiska. Powstają w wielu przedsiębiorstwach – np. w serwisach samochodowych, zakładach produkcyjnych lub gospodarstwach rolnych. Jak jednak należy je zbierać, magazynować i utylizować?",
    "content": "Zużyte oleje i smary to odpady niebezpieczne dla ludzi i środowiska. Powstają w wielu przedsiębiorstwach – np. w serwisach samochodowych, zakładach produkcyjnych lub gospodarstwach rolnych. Jak jednak należy je zbierać, magazynować i utylizować?",
    "published": "2025-10-13T11:49:00+02:00",
    "id": "0001d1916b7270ef00a846ca972e5f8dacd01902",
    "preselect": true,
    "places_german": [
      "Leschnitz",
      "Gross Strehlitz",
      "Oppeln"
    ]
  }
]