[
  {
    "source": "https://falling-bush-1efa.thedatasculptor.workers.dev/",
    "link": "https://lesnica.pl/15286/uwaga-rolnicy-gmina-lesnica-zamierza-zorganizowac-odbior-folii-rolniczej.html",
    "title": "UWAGA ROLNICY! GMINA LEŚNICA ZAMIERZA ZORGANIZOWAĆ ODBIÓR FOLII ROLNICZEJ!",
    "summary": " ",
    "content": " ",
    "published": "2026-01-15T12:00:00+00:00",
    "id": "38b2e7bc37286c32b79a27cbbed41565807e3d8c",
    "preselect": true,
    "places_german": [
      "Leschnitz"
    ]
  }
]