[
  {
    "source": "https://www.strzelce360.pl/rss/articles/pl",
    "link": "https://www.strzelce360.pl/artykul/10720,nowosci-w-bibliotece-w-jemielnicy-jest-cos-dla-dzieci-i-dla-doroslych",
    "title": "Nowości w bibliotece w Jemielnicy. Jest coś dla dzieci i dla dorosłych",
    "summary": "Gminna Biblioteka Publiczna w Jemielnicy otrzymała 15,6 tys. zł dofinansowania w ramach Narodowego Programu Rozwoju Czytelnictwa 2.0.",
    "content": "Gminna Biblioteka Publiczna w Jemielnicy otrzymała 15,6 tys. zł dofinansowania w ramach Narodowego Programu Rozwoju Czytelnictwa 2.0.",
    "published": "2025-10-20T19:15:00+02:00",
    "id": "1b128a9012174b810cee746bed7a79eaa5a1f490",
    "preselect": true,
    "places_german": [
      "Jemielnitz"
    ]
  }
]