[
  {
    "source": "https://wild-union-5400.thedatasculptor.workers.dev/",
    "link": "https://strzelceopolskie.naszemiasto.pl/ukazal-sie-nowy-slownik-gwary-slaskiej-wiecie-co-to-ucek-krepel-i-haberfloki/ar/c1p2-27888843",
    "title": "Ukazał się nowy słownik gwary śląskiej. Wiecie, co to ucek, krepel i haberfloki?",
    "summary": "",
    "content": "",
    "published": "2025-08-20T15:18:06+00:00",
    "id": "4ec94d9a42f1b7c906da8911d07f90fbfc7c908a",
    "preselect": false
  },
  {
    "source": "https://wild-union-5400.thedatasculptor.workers.dev/",
    "link": "https://strzelceopolskie.naszemiasto.pl/ta-marka-stawia-sobie-za-cel-wyeliminowanie-wypadkow-drogowych-jak-chce-to-zrobic/ar/c4p2-27888899",
    "title": "Ta marka stawia sobie za cel wyeliminowanie wypadków drogowych",
    "summary": "",
    "content": "",
    "published": "2025-08-20T15:18:06+00:00",
    "id": "026752a231d7938716fc636ac5e79c6d794805c0",
    "preselect": false
  },
  {
    "source": "https://wild-union-5400.thedatasculptor.workers.dev/",
    "link": "https://motofakty.pl/stacje-paliw-licza-zyski-w-jaki-dzien-jest-najwiekszy-ruch/ar/c4p2-27887933",
    "title": "Stacje paliw liczą zyski. W jaki dzień jest największy ruch?",
    "summary": "",
    "content": "",
    "published": "2025-08-20T15:18:06+00:00",
    "id": "d5bf987c2c6c527da0fa01133dfc5bf58009c734",
    "preselect": false
  },
  {
    "source": "https://wild-union-5400.thedatasculptor.workers.dev/",
    "link": "https://strzelceopolskie.naszemiasto.pl/oto-najsmieszniejsze-wakacyjne-memy-zobacz-a-nie-pozalujesz/ar/c1-9843381",
    "title": "Najlepsze wakacyjne MEMY",
    "summary": "",
    "content": "",
    "published": "2025-08-20T15:18:06+00:00",
    "id": "69a944447e834a87be734a1a4a10c01a3387d8e8",
    "preselect": false
  },
  {
    "source": "https://wild-union-5400.thedatasculptor.workers.dev/",
    "link": "https://strzelceopolskie.naszemiasto.pl/ruszylo-ogolnopolskie-badanie-stanu-zdrowia-do-udzialu-wytypowano-szesc-opolskich-gmin/ar/c14p2-27886127",
    "title": "Ruszyło ogólnopolskie badanie stanu zdrowia. Do udziału wytypowano też opolskie gminy",
    "summary": "",
    "content": "",
    "published": "2025-08-20T15:18:06+00:00"
  },
  {
    "source": "https://wild-union-5400.thedatasculptor.workers.dev/",
    "link": "https://strzelceopolskie.naszemiasto.pl/oto-wszystkie-najpiekniejsze-polki-poznaj-laureatki-konkursu-miss-polski-od-1990-roku-wsrod-nich-sa-opolanki/ar/c1p2-27887121",
    "title": "Oto wszystkie najpiękniejsze Polki. Poznaj laureatki konkursu Miss Polski",
    "summary": "",
    "content": "",
    "published": "2025-08-20T15:18:06+00:00",
    "id": "6fbde9c5410e71045f93bf377ca75f7ba7d3b541",
    "preselect": false
  },
  {
    "source": "https://wild-union-5400.thedatasculptor.workers.dev/",
    "link": "https://motofakty.pl/samochod-uzywany-jak-polski-rynek-aut-z-drugiej-reki-wypada-na-tle-innych-panstw/ar/c4p2-27882131",
    "title": "Samochód używany. Jak polski rynek aut z drugiej ręki wypada na tle innych państw?",
    "summary": "",
    "content": "",
    "published": "2025-08-20T15:18:06+00:00",
    "id": "cf78f21aa9f3493a90433dfa9023a020869fa423",
    "preselect": false
  },
  {
    "source": "https://wild-union-5400.thedatasculptor.workers.dev/",
    "link": "https://strzelceopolskie.naszemiasto.pl/ranking-miast-polskich-2025-gdzie-zyje-sie-najlepiej-gdzie-jest-najbezpieczniej/ar/c11p2-27885727",
    "title": "Ranking miast polskich: gdzie żyje się najlepiej?",
    "summary": "",
    "content": "",
    "published": "2025-08-20T15:18:06+00:00",
    "id": "89d7d0bf68f608ab9f35c40a1fe5ede8ab0bf192",
    "preselect": false
  },
  {
    "source": "https://wild-union-5400.thedatasculptor.workers.dev/",
    "link": "https://motofakty.pl/szokujace-dane-sprzedazy-nowych-aut-chinczycy-przed-skoda-i-hyundaiem/ar/c4p2-27885031",
    "title": "Szokujące dane sprzedaży nowych aut. Chińczycy przed Skodą i Hyundaiem",
    "summary": "",
    "content": "",
    "published": "2025-08-20T15:18:06+00:00",
    "id": "19d1f568d82eed78b687d321de1a835d6be63834",
    "preselect": false
  },
  {
    "source": "https://wild-union-5400.thedatasculptor.workers.dev/",
    "link": "https://strzelceopolskie.naszemiasto.pl/opolszczyzna-zaczyna-slynac-z-murali-niektore-to-prawdziwe/ar/c1-9839729",
    "title": "Opolszczyzna zaczyna słynąć z murali. W wielu miejscach mamy prawdziwe dzieła sztuki!",
    "summary": "",
    "content": "",
    "published": "2025-08-20T15:18:06+00:00"
  },
  {
    "source": "https://wild-union-5400.thedatasculptor.workers.dev/",
    "link": "https://strzelceopolskie.naszemiasto.pl/siedmiu-kierowcow-wpadlo-na-podwojnym-gazie-najbardziej-pijany-jechal-tylko-po-chleb/ar/c1p2-27883893",
    "title": "Najbardziej pijany jechał tylko po chleb. Siedmiu kierowców wpadło podczas kontroli",
    "summary": "",
    "content": "",
    "published": "2025-08-20T15:18:06+00:00",
    "id": "3768a4d58e225b035c130b8e4f812b7f139cdc4f",
    "preselect": false
  },
  {
    "source": "https://wild-union-5400.thedatasculptor.workers.dev/",
    "link": "https://strzelceopolskie.naszemiasto.pl/dzieci-zamkniete-w-samochodzie-to-ekstremalnie-niebezpieczna-sytuacja-w-strzelcach-opolskich-musiala-interweniowac-policja/ar/c1p2-27883693",
    "title": "Dzieci zamknięte w samochodzie. Liczyła się każda minuta. Interweniowała Policja",
    "summary": "",
    "content": "",
    "published": "2025-08-20T15:18:06+00:00",
    "id": "b17f825a362c770928824a062e827cb83ef4e9e4",
    "preselect": false
  },
  {
    "source": "https://wild-union-5400.thedatasculptor.workers.dev/",
    "link": "https://strzelceopolskie.naszemiasto.pl/mariusz-pujszo-kto-odnosi-sukces-to-nie-ten-kto-wczesnie-rano-wstaje-ale-ten-kto-wstaje-usmiechniety/ar/c15p2-27883213",
    "title": "Pujszo: Sukces odnosi ten, kto rano wstaje uśmiechnięty",
    "summary": "",
    "content": "",
    "published": "2025-08-20T15:18:06+00:00",
    "id": "3ea5b2b6c153720280cb86913b51cdfa43221d27",
    "preselect": false
  },
  {
    "source": "https://wild-union-5400.thedatasculptor.workers.dev/",
    "link": "https://strzelceopolskie.naszemiasto.pl/kolejna-linia-kolejowa-na-opolszczyznie-zostanie-zmodernizowana-pociagi-pojada-z-predkoscia-160-km-h/ar/c1p2-27813849",
    "title": "Kolejna opolska linia kolejowa zostanie zmodernizowana. Pociągi pojadą tędy 160 km/h",
    "summary": "",
    "content": "",
    "published": "2025-08-20T15:18:06+00:00",
    "id": "1f09256e4a304c2cbf70b45dfb585a5ebc7edf6d",
    "preselect": false
  },
  {
    "source": "https://wild-union-5400.thedatasculptor.workers.dev/",
    "link": "https://strzelceopolskie.naszemiasto.pl/sa-nowe-sklepy-w-galerii-handlowej-karolinka-w-opolu/ar/c1-9319333",
    "title": "Są nowe sklepy w galerii handlowej Karolinka w Opolu. Zadowoleni będą fani sportu",
    "summary": "",
    "content": "",
    "published": "2025-08-20T15:18:06+00:00",
    "id": "736bdb68464ba448ac6f0bf431aeba0f69c0e862",
    "preselect": false
  }
]