[
  {
    "source": "https://wild-union-5400.thedatasculptor.workers.dev/",
    "link": "https://strzelceopolskie.naszemiasto.pl/goracy-weekend-warto-na-opolszczyznie-spedzic-nad-woda-te-kapieliska-sa-czynne-i-strzezone/ar/c1p2-27730993",
    "title": "Gorący weekend warto spędzić nad wodą. Te kąpieliska są czynne i strzeżone",
    "summary": "",
    "content": "",
    "published": "2025-08-16T07:20:43+00:00",
    "id": "3a9dc0b26da11939470d38071558fe668ea73314",
    "preselect": false
  },
  {
    "source": "https://wild-union-5400.thedatasculptor.workers.dev/",
    "link": "https://strzelceopolskie.naszemiasto.pl/ks-krzysztof-kapica-kazdy-z-nas-jest-wezwany-by-w-codziennym-zyciu-podazac-do-swietosci-patnicy-pokonali-przedostatni-etap-pielgrzymki/ar/c1p2-27876949",
    "title": "Wszyscy pielgrzymi spotkali się na wspólnej Mszy świętej. Są coraz bliżej celu",
    "summary": "",
    "content": "",
    "published": "2025-08-16T07:20:43+00:00",
    "id": "3d257b6debebf64120175e4bce493312460c14a1",
    "preselect": false
  },
  {
    "source": "https://wild-union-5400.thedatasculptor.workers.dev/",
    "link": "https://strzelceopolskie.naszemiasto.pl/niespodzianka-po-zerwaniu-asfaltu-przez-budowe-ronda-droga-wojewodzka-bedzie-calkowicie-zamknieta/ar/c1p2-27875861",
    "title": "Niespodzianka po zerwaniu asfaltu. Przez budowę ronda droga będzie zamknięta",
    "summary": "",
    "content": "",
    "published": "2025-08-16T07:20:43+00:00",
    "id": "87f82a745ebc3ed519ca635936c18fdc5606fc36",
    "preselect": false
  },
  {
    "source": "https://wild-union-5400.thedatasculptor.workers.dev/",
    "link": "https://strzelceopolskie.naszemiasto.pl/idac-na-jasna-gore-przypominaja-o-opolskim-bohaterze-powstan-slaskich-seweryn-jedrysik-zginal-w-kl-dachau/ar/c1p2-27875849",
    "title": "105 lat temu wybuchło II Powstanie Śląskie. Pielgrzymi przypominają bohatera",
    "summary": "",
    "content": "",
    "published": "2025-08-16T07:20:43+00:00",
    "id": "05073717e686280069e5be8e9944a8bfed6c069c",
    "preselect": false
  },
  {
    "source": "https://wild-union-5400.thedatasculptor.workers.dev/",
    "link": "https://strzelceopolskie.naszemiasto.pl/sprawdzilismy-jaka-jest-placa-minimalna-w-roznych-krajach-polska-jest-coraz-wyzej-na-tej-liscie-ranking-2025/ar/c1p2-27874851",
    "title": "Jaka jest płaca minimalna w różnych krajach? Polska jest coraz wyżej w tym rankingu",
    "summary": "",
    "content": "",
    "published": "2025-08-16T07:20:43+00:00",
    "id": "4839b9d458313c75a40dff04e3ae2057d1d37eb7",
    "preselect": false
  },
  {
    "source": "https://wild-union-5400.thedatasculptor.workers.dev/",
    "link": "https://strzelceopolskie.naszemiasto.pl/to-bedzie-wielka-impreza-na-scenie-teresa-werner-lobuzy-daj-to-glosniej-i-chatelet/ar/c1p2-27872757",
    "title": "Będzie wielka impreza. Na scenie: Teresa Werner, Łobuzy, Daj to głośniej i Chatelet",
    "summary": "",
    "content": "",
    "published": "2025-08-16T07:20:43+00:00",
    "id": "24f1b4ad12ddf5ac8115e08b686acd3058041e65",
    "preselect": false
  },
  {
    "source": "https://wild-union-5400.thedatasculptor.workers.dev/",
    "link": "https://strzelceopolskie.naszemiasto.pl/toyoty-proace-max-z-zabudowa-typu-kontener-te-dostawczaki-maja-trzyletnia-gwarancje/ar/c4p2-27874427",
    "title": "Toyoty Proace Max z zabudową typu kontener. Te dostawczaki mają trzyletnią gwarancję",
    "summary": "",
    "content": "",
    "published": "2025-08-16T07:20:43+00:00",
    "id": "c440bcb6f52e0cfdfd6f5483e3f8a9b598481ab0",
    "preselect": false
  },
  {
    "source": "https://wild-union-5400.thedatasculptor.workers.dev/",
    "link": "https://strzelceopolskie.naszemiasto.pl/samochod-uzywany-te-auta-elektryczne-sprzedaja-sie-najlepiej-w-polsce/ar/c4p2-27866829",
    "title": "Samochód używany. Te auta elektryczne sprzedają się najlepiej",
    "summary": "",
    "content": "",
    "published": "2025-08-16T07:20:43+00:00",
    "id": "f57e4473bdd539091d7549322843781ae33e85b9",
    "preselect": false
  },
  {
    "source": "https://wild-union-5400.thedatasculptor.workers.dev/",
    "link": "https://motofakty.pl/kolejna-podwyzka-oplat-na-autostradzie-a2-druga-w-tym-roku-mamy-oswiadczenie-spolki/ar/c4p2-27872951",
    "title": "Kolejna podwyżka opłat na autostradzie A2. Druga w tym roku. Mamy oświadczenie spółki",
    "summary": "",
    "content": "",
    "published": "2025-08-16T07:20:43+00:00",
    "id": "42c7e90c5204f0eb26df2ac3e00a2e21422633fe",
    "preselect": false
  },
  {
    "source": "https://wild-union-5400.thedatasculptor.workers.dev/",
    "link": "https://strzelceopolskie.naszemiasto.pl/na-opolszczyznie-mamy-mnostwo-stulatkow-w-ktorym-miescie/ar/c1-9852137",
    "title": "Na Opolszczyźnie mamy mnóstwo stulatków. W którym mieście żyje ich najwięcej?",
    "summary": "",
    "content": "",
    "published": "2025-08-16T07:20:43+00:00",
    "id": "8246257863e270fb1ce1680de05387d0ccffe070",
    "preselect": false
  },
  {
    "source": "https://wild-union-5400.thedatasculptor.workers.dev/",
    "link": "https://motofakty.pl/policyjna-akcja-w-calej-polsce-to-bedzie-kontrolowac-drogowka/ar/c4p2-27869237",
    "title": "Policyjna akcja w całej Polsce. To będzie kontrolować drogówka",
    "summary": "",
    "content": "",
    "published": "2025-08-16T07:20:43+00:00",
    "id": "3f87f582b4eff517bbdea24629e4509aafb08150",
    "preselect": false
  },
  {
    "source": "https://wild-union-5400.thedatasculptor.workers.dev/",
    "link": "https://motofakty.pl/ceny-paliw-tu-za-tankowanie-zaplacisz-najmniej-w-polowie-sierpnia/ar/c4p2-27870259",
    "title": "Ceny paliw. Tu za tankowanie zapłacisz najmniej w połowie sierpnia",
    "summary": "",
    "content": "",
    "published": "2025-08-16T07:20:43+00:00",
    "id": "2008efbf65cfc06168a4b0b7580a56cc848a491b",
    "preselect": false
  },
  {
    "source": "https://wild-union-5400.thedatasculptor.workers.dev/",
    "link": "https://strzelceopolskie.naszemiasto.pl/sezon-owocowo-warzywny-w-pelni-ceny-pomidorow-ogorkow-i-fasolki-w-tym-roku-poszybowaly/ar/c1p2-27870861",
    "title": "O TYM SIĘ MÓWI Sezon owocowo-warzywny w pełni. Ceny w tym roku poszybowały",
    "summary": "",
    "content": "",
    "published": "2025-08-16T07:20:43+00:00",
    "id": "a321d32ebd9004e054db7a821aab6b800aaab4a8",
    "preselect": false
  },
  {
    "source": "https://wild-union-5400.thedatasculptor.workers.dev/",
    "link": "https://strzelceopolskie.naszemiasto.pl/w-czasie-pielgrzymki-na-jasna-gore-patnicy-otrzymuja-ogrom-wsparcia-to-setki-wolontariuszy-ktorzy-pomagaja-karmia-i-zapraszaja-na-noclegi/ar/c1p2-27872215",
    "title": "Częstują pielgrzymów jedzeniem i zapraszają na noclegi. To setki ludzi dobrej woli",
    "summary": "",
    "content": "",
    "published": "2025-08-16T07:20:43+00:00",
    "id": "23c4e53246f8d6b8be00652b81fc0805b9bffd4d",
    "preselect": false
  },
  {
    "source": "https://wild-union-5400.thedatasculptor.workers.dev/",
    "link": "https://strzelceopolskie.naszemiasto.pl/dozynki-2025-na-opolszczyznie-wystapia-u-nas-muzyczne-gwiazdy-m-in-de-mono-kasia-kowalska-i-norbi/ar/c1p2-27872003",
    "title": "Dożynki 2025 na Opolszczyźnie. Wystąpią u nas gwiazdy",
    "summary": "",
    "content": "",
    "published": "2025-08-16T07:20:43+00:00",
    "id": "630739ee0fc23dd461e1d971288e54ccbdb21fe4",
    "preselect": false
  }
]