[
  {
    "source": "https://wild-union-5400.thedatasculptor.workers.dev/",
    "link": "https://strzelceopolskie.naszemiasto.pl/ten-fotoradar-jest-malo-widoczny-stoi-przy-wezle-autostrady-a4-i-robi-mnostwo-zdjec/ar/c1p2-28232959",
    "title": "Ten fotoradar jest mało widoczny. Stoi przy węźle autostrady A4 i robi mnóstwo zdjęć",
    "summary": "",
    "content": "",
    "published": "2026-01-06T09:24:15+00:00",
    "id": "3e60211bdfd2a51230cccde3e6efff3666eea1e2",
    "preselect": false
  },
  {
    "source": "https://wild-union-5400.thedatasculptor.workers.dev/",
    "link": "https://strzelceopolskie.naszemiasto.pl/dino-buduje-kolejne-sklepy-znamy-lokalizacje/ar/c1p2-28311121",
    "title": "Dino buduje kolejne sklepy. Znamy lokalizacje",
    "summary": "",
    "content": "",
    "published": "2026-01-06T09:24:15+00:00",
    "id": "0fd0b0898814f97d5671a37db216cd8a705eeb56",
    "preselect": false
  },
  {
    "source": "https://wild-union-5400.thedatasculptor.workers.dev/",
    "link": "https://strzelceopolskie.naszemiasto.pl/na-opolszczyznie-powstanie-jedna-z-najwiekszych-farm-fotowoltaicznych-w-polsce-zobacz-w-ktorym-miejscu/ar/c1p2-28236975",
    "title": "Na Opolszczyźnie powstanie jedna z największych farm fotowoltaicznych w Polsce. Zobacz, w którym miejscu",
    "summary": "",
    "content": "",
    "published": "2026-01-06T09:24:15+00:00"
  },
  {
    "source": "https://wild-union-5400.thedatasculptor.workers.dev/",
    "link": "https://strzelceopolskie.naszemiasto.pl/orszaki-trzech-kroli-na-opolszczyznie-zobacz-o-ktorej-i-gdzie-wyrusza/ar/c1p2-28317443",
    "title": "Orszaki Trzech Króli na Opolszczyźnie. Zobacz, o której i gdzie wyruszą",
    "summary": "",
    "content": "",
    "published": "2026-01-06T09:24:15+00:00"
  },
  {
    "source": "https://wild-union-5400.thedatasculptor.workers.dev/",
    "link": "https://strzelceopolskie.naszemiasto.pl/w-opolskich-lasach-coraz-czesciej-spotykamy-wilki-jak-sie-zachowac-na-ich-widok/ar/c1p2-28320577",
    "title": "W opolskich lasach coraz częściej spotykamy wilki. Jak się zachować na ich widok?",
    "summary": "",
    "content": "",
    "published": "2026-01-06T09:24:15+00:00"
  },
  {
    "source": "https://wild-union-5400.thedatasculptor.workers.dev/",
    "link": "https://strzelceopolskie.naszemiasto.pl/tu-zjesz-najlepsza-pizze-na-opolszczyznie-te-pizzerie/ar/c1-9610203",
    "title": "Tu zjesz najlepszą pizzę na Opolszczyźnie. Te pizzerie najbardziej polecają Opolanie",
    "summary": "",
    "content": "",
    "published": "2026-01-06T09:24:15+00:00"
  },
  {
    "source": "https://wild-union-5400.thedatasculptor.workers.dev/",
    "link": "https://strzelceopolskie.naszemiasto.pl/idzie-silny-mroz-policja-apeluje-zeby-nie-dac-zamarznac/ar/c1-9094533",
    "title": "Idzie silny mróz. Policja apeluje, żeby nie dać zamarznąć osobom samotnym i bezdomnym",
    "summary": "",
    "content": "",
    "published": "2026-01-06T09:24:15+00:00",
    "id": "e47e8d83ccd5074e401b97ed237e7568546475ce",
    "preselect": false
  },
  {
    "source": "https://wild-union-5400.thedatasculptor.workers.dev/",
    "link": "https://strzelceopolskie.naszemiasto.pl/mandaty-2026-w-zycie-wchodza-nowe-surowe-przepisy-mozna/ar/c1-9284925",
    "title": "Mandaty 2026. W życie wchodzą nowe, surowe przepisy. Można nawet trafić do więzienia",
    "summary": "",
    "content": "",
    "published": "2026-01-06T09:24:15+00:00",
    "id": "ce86a525104e3bf58f8ffc8a45f2f5cd82a7e54e",
    "preselect": false
  },
  {
    "source": "https://wild-union-5400.thedatasculptor.workers.dev/",
    "link": "https://strzelceopolskie.naszemiasto.pl/najmlodsze-miasta-na-opolszczyznie-najnowsze-uzyskalo-prawa/ar/c1-9160529",
    "title": "Najmłodsze miasta na Opolszczyźnie. Najnowsze uzyskało prawa miejskie kilka dni temu",
    "summary": "",
    "content": "",
    "published": "2026-01-06T09:24:15+00:00"
  },
  {
    "source": "https://wild-union-5400.thedatasculptor.workers.dev/",
    "link": "https://strzelceopolskie.naszemiasto.pl/nowe-dane-o-zarobkach-mieszkancow-opolszczyzny-zobacz-gdzie-zarabia-sie-najlepiej/ar/c1p2-28299337",
    "title": "Nowe dane o zarobkach mieszkańców Opolszczyzny. Zobacz, gdzie zarabia się najlepiej",
    "summary": "",
    "content": "",
    "published": "2026-01-06T09:24:15+00:00"
  },
  {
    "source": "https://wild-union-5400.thedatasculptor.workers.dev/",
    "link": "https://strzelceopolskie.naszemiasto.pl/kto-naprawde-pracuje-w-sejmie-sprawdzilismy-aktywnosc-poslow-z-opolszczyzny/ar/c1p2-28319037",
    "title": "GORĄCY TEMAT Kto naprawdę pracuje w Sejmie? Sprawdziliśmy aktywność posłów z Opolszczyzny",
    "summary": "",
    "content": "",
    "published": "2026-01-06T09:24:15+00:00"
  },
  {
    "source": "https://wild-union-5400.thedatasculptor.workers.dev/",
    "link": "https://strzelceopolskie.naszemiasto.pl/weselne-menu-tradycyjne-nowoczesne-dla-dzieci-z-atrakcjami/ar/c6-9186469",
    "title": "Weselne menu: tradycyjne, nowoczesne, dla dzieci, z atrakcjami i vege. Sprawdź, jakie menu zamówić na wesele 2",
    "summary": "",
    "content": "",
    "published": "2026-01-06T09:24:15+00:00",
    "id": "a93a45516f41d9dbeab396a52ae6e0dbed1a77e0",
    "preselect": false
  },
  {
    "source": "https://wild-union-5400.thedatasculptor.workers.dev/",
    "link": "https://strzelceopolskie.naszemiasto.pl/nie-lubie-poniedzialkow-masz-syndrom-poniedzialku-nie/ar/c3-9232131",
    "title": "Nie lubię poniedziałków! Masz syndrom poniedziałku? Nie jesteś wyjątkiem 1",
    "summary": "",
    "content": "",
    "published": "2026-01-06T09:24:15+00:00",
    "id": "ce67dd79bba9fcb1f8dc20027e0544a73e1faa00",
    "preselect": false
  },
  {
    "source": "https://wild-union-5400.thedatasculptor.workers.dev/",
    "link": "https://strzelceopolskie.naszemiasto.pl/swiateczne-bombki-z-dawnych-lat-tak-wygladala-choinka-w/ar/c15-9549327",
    "title": "Świąteczne bombki z dawnych lat. Tak wyglądała choinka w czasach PRL-u",
    "summary": "",
    "content": "",
    "published": "2026-01-06T09:24:15+00:00",
    "id": "e6fdcc26aeb433b8e5447d7638a52f28e72f206d",
    "preselect": false
  },
  {
    "source": "https://wild-union-5400.thedatasculptor.workers.dev/",
    "link": "https://motofakty.pl/korki-na-drodze-zima-co-je-powoduje-i-czy-kierowcy-elektrykow-maja-sie-czego-bac/ar/c4p2-28313107",
    "title": "Korki na drodze zimą. Co je powoduje i czy kierowcy elektryków mają się czego bać?",
    "summary": "",
    "content": "",
    "published": "2026-01-06T09:24:15+00:00",
    "id": "6d88cc110452d185b6c2f8bf5ba08ced1ac60afc",
    "preselect": false
  }
]