[
  {
    "source": "https://nto.pl/rss/nowatrybunaopolska.xml",
    "link": "https://nto.pl/rolnictwo-w-czasach-prlu-tak-wygladala-polska-wies-kiedy-nie-bylo-unijnych-doplat/ar/c8-15225740",
    "title": "Rolnictwo w czasach PRL-u. Tak wyglądała polska wieś, kiedy nie było unijnych dopłat",
    "summary": "Fury, pługi i inne maszyny rolnicze ciągnięte przez konie to była codzienność na opolskiej wsi. Z nastającą mechanizacją zastępowały je traktory. Zapraszamy do galerii czarno-białych fotografii.",
    "content": "Fury, pługi i inne maszyny rolnicze ciągnięte przez konie to była codzienność na opolskiej wsi. Z nastającą mechanizacją zastępowały je traktory. Zapraszamy do galerii czarno-białych fotografii.",
    "published": "2025-12-08T14:32:00+01:00",
    "id": "0084f32bf6ad69025449ef8a9f58fe02d4f51120",
    "preselect": true,
    "places_german": [
      "Oppeln"
    ]
  },
  {
    "source": "https://bip.lesnica.pl/rss/2025/rejestr-zmian-strony.html",
    "link": "https://bip.lesnica.pl/15178/08122025-informacja-o-wyniku-przetargu.html",
    "title": "08.12.2025 INFORMACJA O WYNIKU PRZETARGU",
    "summary": "",
    "content": "",
    "published": "2025-12-08T14:07:29+01:00",
    "id": "32dcca6234dc0341cd3eb26831a2ba75c2af12c7",
    "preselect": true,
    "places_german": [
      "Leschnitz",
      "Gross Strehlitz"
    ]
  }
]