[
  {
    "source": "https://www.strzelce360.pl/rss/articles/pl",
    "link": "https://www.strzelce360.pl/artykul/11550,grozne-dachowanie-na-autostradzie-a4-sluzby-apeluja-o-ostroznosc",
    "title": "Groźne dachowanie na autostradzie A4. Służby apelują o ostrożność",
    "summary": "Do zdarzenia doszło w czwartek, 7 maja, po godz. 18.00 na 263. kilometrze autostrady A4 w kierunku Wrocławia (rejon Ligoty Górnej). Pojazdem podróżowała jedna osoba.",
    "content": "Do zdarzenia doszło w czwartek, 7 maja, po godz. 18.00 na 263. kilometrze autostrady A4 w kierunku Wrocławia (rejon Ligoty Górnej). Pojazdem podróżowała jedna osoba.",
    "published": "2026-05-07T18:56:00+02:00",
    "id": "fe1144cd638a3b458e8c645125bbd66cb3f8253e",
    "preselect": true,
    "places_german": [
      "Ober Liegau"
    ]
  }
]