[
  {
    "source": "https://www.strzelce360.pl/rss/articles/pl",
    "link": "https://www.strzelce360.pl/artykul/10900,czolowe-zderzenie-busa-z-osobowka-sprawca-nie-mial-uprawnien",
    "title": "Czołowe zderzenie busa z osobówką. Sprawca nie miał uprawnień",
    "summary": "Do groźnego zdarzenia doszło na drodze między Zawadzkiem a Kolonowskiem. Czołowo zderzyły się bus i osobówka. Sprawca nie powinien w ogóle siedzieć za kierownicą: nie miał uprawnień.",
    "content": "Do groźnego zdarzenia doszło na drodze między Zawadzkiem a Kolonowskiem. Czołowo zderzyły się bus i osobówka. Sprawca nie powinien w ogóle siedzieć za kierownicą: nie miał uprawnień.",
    "published": "2025-11-27T16:43:00+01:00",
    "id": "120280c48fa7556568b4458a9ef0e2cfddd727d2",
    "preselect": true,
    "places_german": [
      "Zawadzki",
      "Kolonowski",
      "Oppeln"
    ]
  }
]