[
  {
    "source": "https://nto.pl/rss/nowatrybunaopolska.xml",
    "link": "https://nto.pl/quiz/11851,mieszko_otyly_plac_lenina_i_opolski_hipnotyzer_sprawdz_ile_wiesz_o_opolu_quiz,q,t.html",
    "title": "Mieszko Otyły, plac Lenina i opolski hipnotyzer. Sprawdź, ile wiesz o Opolu [QUIZ]",
    "summary": "Wiesz, kt&oacute;ry zdobywca Oscara wychował się w Opolu? Kt&oacute;rego naukowca z Opola wspierał sam Albert Einstein? I dlaczego prezydent Opola na Festiwalu Opolskim wypalił: &bdquo;Witam was ciule&quot;? Rozwiąż ten quiz i sprawdź, ile wiesz o Opolu.",
    "content": "Wiesz, kt&oacute;ry zdobywca Oscara wychował się w Opolu? Kt&oacute;rego naukowca z Opola wspierał sam Albert Einstein? I dlaczego prezydent Opola na Festiwalu Opolskim wypalił: &bdquo;Witam was ciule&quot;? Rozwiąż ten quiz i sprawdź, ile wiesz o Opolu.",
    "published": "2026-07-18T17:34:01+02:00",
    "id": "d0c22ab9c89a8e6eb39595729a28ffc46f9ba419",
    "preselect": true,
    "places_german": [
      "Oppeln"
    ]
  }
]