[
  {
    "source": "https://wild-union-5400.thedatasculptor.workers.dev/",
    "link": "https://strzelceopolskie.naszemiasto.pl/trendy-ktore-zmieniaja-nasze-domy-te-meble-maja-styl-i-sa/ar/c9-9314331",
    "title": "Trendy, które zmieniają nasze domy. Te meble mają styl i są ponadczasowe. Zobacz! 5",
    "summary": "",
    "content": "",
    "published": "2025-11-25T03:47:00+00:00",
    "id": "732930f70914aaa6acae17844805df5240f76019",
    "preselect": false
  },
  {
    "source": "https://wild-union-5400.thedatasculptor.workers.dev/",
    "link": "https://strzelceopolskie.naszemiasto.pl/niezwykla-moda-z-czasow-prl-takie-niesamowite-rzeczy-nosily/ar/c6-9200057",
    "title": "Niezwykła moda z czasów PRL. Takie niesamowite rzeczy nosiły dziewczyny! Moda wraca? Sprawdź!",
    "summary": "",
    "content": "",
    "published": "2025-11-25T03:47:00+00:00",
    "id": "39880d79e7f7c092474f4ac0026eecd60c0a6d5c",
    "preselect": false
  },
  {
    "source": "https://wild-union-5400.thedatasculptor.workers.dev/",
    "link": "https://regiodom.pl/klienci-nie-musza-bac-sie-awarii-fachowcy-sa-dostepni-przez-cala-dobe/ar/c9p2-28196209",
    "title": "Klienci nie muszą bać się awarii. Fachowcy są dostępni przez całą dobę",
    "summary": "",
    "content": "",
    "published": "2025-11-25T03:47:00+00:00",
    "id": "c3818fb3cdfd8c726fef67368fe84ce21df6de70",
    "preselect": false
  },
  {
    "source": "https://wild-union-5400.thedatasculptor.workers.dev/",
    "link": "https://strzelceopolskie.naszemiasto.pl/kontrowersje-wokol-uchwaly-dotyczacej-gory-swietej-anny-politycy-pis-to-obstrukcja/ar/c1p2-28204195",
    "title": "Kontrowersje wokół uchwały dotyczącej Góry Świętej Anny. Politycy PiS: To obstrukcja",
    "summary": "",
    "content": "",
    "published": "2025-11-25T03:47:00+00:00",
    "id": "dd723196c37143bdb988c763763a796848c4f756",
    "preselect": false
  },
  {
    "source": "https://wild-union-5400.thedatasculptor.workers.dev/",
    "link": "https://strzelceopolskie.naszemiasto.pl/uzywany-hyundai-i10-iii-od-2019-r-jakie-ma-wady-i-zalety/ar/c4p2-28204021",
    "title": "Używany Hyundai i10 III (od 2019 r.). Jakie ma wady i zalety?",
    "summary": "",
    "content": "",
    "published": "2025-11-25T03:47:00+00:00",
    "id": "d238fddc20daaf1259e51ecacb938e12f3be4d66",
    "preselect": false
  },
  {
    "source": "https://wild-union-5400.thedatasculptor.workers.dev/",
    "link": "https://strzelceopolskie.naszemiasto.pl/szok-nietrzezwi-rodzice-wiezli-dwojke-malych-dzieci-jazde-przerwala-dopiero-policja/ar/c1p2-28204137",
    "title": "Szok. Nietrzeźwi rodzice wieźli dwójkę małych dzieci. Jazdę przerwała dopiero policja",
    "summary": "",
    "content": "",
    "published": "2025-11-25T03:47:00+00:00",
    "id": "cba5da6e60eb7c87d7ec203d5847e0ec70c62024",
    "preselect": false
  },
  {
    "source": "https://wild-union-5400.thedatasculptor.workers.dev/",
    "link": "https://strzelceopolskie.naszemiasto.pl/na-sprzedazy-starych-orderow-mozna-niezle-zarobic-tyle-proponuja-teraz-kolekcjonerzy/ar/c1p2-28164219",
    "title": "Na sprzedaży starych orderów można nieźle zarobić. Tyle proponują teraz kolekcjonerzy",
    "summary": "",
    "content": "",
    "published": "2025-11-25T03:47:00+00:00",
    "id": "773ac7d4623182b9cf56b8028a4de67e2010a537",
    "preselect": false
  },
  {
    "source": "https://wild-union-5400.thedatasculptor.workers.dev/",
    "link": "https://strzelceopolskie.naszemiasto.pl/minister-obrony-narodowej-wladyslaw-kosiniak-kamysz-na-regionalnym-forum-ekonomicznym-nowa-energia-kielce-2025-zobacz-zapis-transmisji/ar/c3p2-28203059",
    "title": "Minister obrony narodowej, Władysław Kosiniak-Kamysz na Regionalnym Forum Ekonomicznym Nowa Energia Kielce 2025. Zobacz zapis transmisji",
    "summary": "",
    "content": "",
    "published": "2025-11-25T03:47:00+00:00",
    "id": "8f0f1261b5b6f711c7c4aa504fff8e22a362480a",
    "preselect": false
  },
  {
    "source": "https://wild-union-5400.thedatasculptor.workers.dev/",
    "link": "https://motofakty.pl/czy-nowe-samochody-sa-bezpieczne-mamy-wyniki-testow-zderzeniowych/ar/c4p2-28202527",
    "title": "Czy nowe samochody są bezpieczne? Mamy wyniki testów zderzeniowych",
    "summary": "",
    "content": "",
    "published": "2025-11-25T03:47:00+00:00",
    "id": "fec5877a5baf124ee1d051676d2ae97adb3a58d9",
    "preselect": false
  },
  {
    "source": "https://wild-union-5400.thedatasculptor.workers.dev/",
    "link": "https://strzelceopolskie.naszemiasto.pl/ciezarowki-utknely-na-autostradzie-a4-pod-gora-sw-anny-plugi-nie-mogly-dojechac/ar/c1p2-28203243",
    "title": "Ciężarówki utknęły na autostradzie A4 pod Górą św. Anny. Pługi nie mogły dojechać",
    "summary": "",
    "content": "",
    "published": "2025-11-25T03:47:00+00:00",
    "id": "8ef4996e1a73460020e8ceeacd4fc65715e73834",
    "preselect": false
  },
  {
    "source": "https://wild-union-5400.thedatasculptor.workers.dev/",
    "link": "https://strzelceopolskie.naszemiasto.pl/przesympatyczne-i-bardzo-usmiechniete-oto-dziewczyny-z/ar/c1-9843455",
    "title": "Przesympatyczne i bardzo uśmiechnięte - oto dziewczyny z naszego konkursu \"Dziewczyna z Sąsiedztwa\" ZDJECIA",
    "summary": "",
    "content": "",
    "published": "2025-11-25T03:47:00+00:00",
    "id": "3641d8be34e84f830c00fd94e2d95489ca739d44",
    "preselect": false
  },
  {
    "source": "https://wild-union-5400.thedatasculptor.workers.dev/",
    "link": "https://motofakty.pl/nowe-skody-w-policji-tym-potrafia-zmylic-kierowcow/ar/c4p2-28202793",
    "title": "Nowe Škody w policji. Tym potrafią zmylić kierowców",
    "summary": "",
    "content": "",
    "published": "2025-11-25T03:47:00+00:00",
    "id": "3bc3355f020a57c6e903ad056539ef98285796b8",
    "preselect": false
  },
  {
    "source": "https://wild-union-5400.thedatasculptor.workers.dev/",
    "link": "https://strzelceopolskie.naszemiasto.pl/12-potraw-na-wigilie-lista-to-tradycyjne-obowiazkowe/ar/c1-8586015",
    "title": "12 potraw na Wigilię - lista. To tradycyjne obowiązkowe potrawy na Wigilię. Polecają Makłowicz, Wachowicz, Brodnicki, Okrasa",
    "summary": "",
    "content": "",
    "published": "2025-11-25T03:47:00+00:00",
    "id": "2a57ce8d266c8d530a6c7f4303a624e72e065ee6",
    "preselect": false
  },
  {
    "source": "https://wild-union-5400.thedatasculptor.workers.dev/",
    "link": "https://strzelceopolskie.naszemiasto.pl/oto-najsmieszniejsze-wakacyjne-memy-ten-humor-na-pewno/ar/c1-9843381",
    "title": "Oto najśmieszniejsze wakacyjne memy. Ten humor na pewno poprawi Twój nastrój. Zobacz a nie pożałujesz",
    "summary": "",
    "content": "",
    "published": "2025-11-25T03:47:00+00:00",
    "id": "106ec6cd36d74c79e67340d0b6a392fc63e6ee72",
    "preselect": false
  },
  {
    "source": "https://wild-union-5400.thedatasculptor.workers.dev/",
    "link": "https://strzelceopolskie.naszemiasto.pl/kilkuset-mlodych-z-opolszczyzny-na-wspolnej-modlitwie-i-zabawie-dzis-jest-ich-swieto/ar/c1p2-28200691",
    "title": "Kilkuset młodych z Opolszczyzny na wspólnej modlitwie i zabawie. Dziś jest ich święto",
    "summary": "",
    "content": "",
    "published": "2025-11-25T03:47:00+00:00"
  }
]