[
  {
    "source": "https://wild-union-5400.thedatasculptor.workers.dev/",
    "link": "https://motofakty.pl/import-pojazdow-maleje-zobacz-co-dzieje-sie-na-rynku/ar/c4p2-28697451",
    "title": "Import pojazdów maleje. Zobacz co dzieje się na rynku",
    "summary": "",
    "content": "",
    "published": "2026-02-05T12:56:29+00:00",
    "id": "805a9cc1b6b6ba2aca03714b4518a65cbebe4af8",
    "preselect": false
  },
  {
    "source": "https://wild-union-5400.thedatasculptor.workers.dev/",
    "link": "https://strzelceopolskie.naszemiasto.pl/tyle-kosztuja-teraz-te-monety-oto-konkretne-oferty/ar/c1p2-28674691",
    "title": "Tyle kosztują teraz te monety. Oto konkretne oferty",
    "summary": "",
    "content": "",
    "published": "2026-02-05T12:56:29+00:00",
    "id": "73e3e3528b62a4117033307d3991a609c4d03431",
    "preselect": false
  },
  {
    "source": "https://wild-union-5400.thedatasculptor.workers.dev/",
    "link": "https://strzelceopolskie.naszemiasto.pl/dokad-i-za-ile-przeprowadzaja-sie-polacy-najnowsze-trendy/ar/c1p2-28700509",
    "title": "Dokąd i za ile przeprowadzają się Polacy? Najnowsze trendy",
    "summary": "",
    "content": "",
    "published": "2026-02-05T12:56:29+00:00",
    "id": "d7910b9bdcc15d4c67e7f0787274be5b805a8ca5",
    "preselect": false
  },
  {
    "source": "https://wild-union-5400.thedatasculptor.workers.dev/",
    "link": "https://motofakty.pl/pierwszy-miesiac-roku-i-od-razu-podwyzka-za-to-kierowcy-placa-wiecej/ar/c4p2-28700127",
    "title": "Pierwszy miesiąc roku i od razu podwyżka. Za to kierowcy płacą więcej",
    "summary": "",
    "content": "",
    "published": "2026-02-05T12:56:29+00:00",
    "id": "dbc3747815b038a4f0e7dbd113725c75124b2227",
    "preselect": false
  },
  {
    "source": "https://wild-union-5400.thedatasculptor.workers.dev/",
    "link": "https://strzelceopolskie.naszemiasto.pl/milicja-zaprasza-na-bal-tak-to-w-prl-bywalo/ar/c6-9204369",
    "title": "Milicja zaprasza na bal! Tak to w PRL bywało...",
    "summary": "",
    "content": "",
    "published": "2026-02-05T12:56:29+00:00",
    "id": "d99345cc439eafb9723874a8a32a3f27eaf1405a",
    "preselect": false
  },
  {
    "source": "https://wild-union-5400.thedatasculptor.workers.dev/",
    "link": "https://strzelceopolskie.naszemiasto.pl/nasze-kolana-maja-termin-waznosci-ortopeda-mowi-wprost/ar/c1p2-28684257",
    "title": "Nasze kolana mają termin ważności. Ortopeda mówi wprost",
    "summary": "",
    "content": "",
    "published": "2026-02-05T12:56:29+00:00",
    "id": "106dd294e95e00c3fb5b2fa2aded7defa1db9f65",
    "preselect": false
  },
  {
    "source": "https://wild-union-5400.thedatasculptor.workers.dev/",
    "link": "https://strzelceopolskie.naszemiasto.pl/obiad-jak-u-mamy-pamietacie-takie-potrawy-sprawdz-przepisy/ar/c17-9355433",
    "title": "Obiad jak u mamy. Pamiętacie takie potrawy? Sprawdź przepisy 2",
    "summary": "",
    "content": "",
    "published": "2026-02-05T12:56:29+00:00",
    "id": "4fb73868a338871053dee75b89c8ebc74e284898",
    "preselect": false
  },
  {
    "source": "https://wild-union-5400.thedatasculptor.workers.dev/",
    "link": "https://strzelceopolskie.naszemiasto.pl/swiateczne-bombki-z-dawnych-lat-tak-wygladala-choinka-w/ar/c15-9549327",
    "title": "Świąteczne bombki z dawnych lat. Tak wyglądała choinka w czasach PRL-u",
    "summary": "",
    "content": "",
    "published": "2026-02-05T12:56:29+00:00",
    "id": "e6fdcc26aeb433b8e5447d7638a52f28e72f206d",
    "preselect": false
  },
  {
    "source": "https://wild-union-5400.thedatasculptor.workers.dev/",
    "link": "https://strzelceopolskie.naszemiasto.pl/proste-przepisy-na-niezwykla-kawe-sprawdz/ar/c17-9180279",
    "title": "Proste przepisy na niezwykłą kawę, sprawdź 1",
    "summary": "",
    "content": "",
    "published": "2026-02-05T12:56:29+00:00",
    "id": "5e837fc16e5585885d589bf89cfb6c487a931c3f",
    "preselect": false
  },
  {
    "source": "https://wild-union-5400.thedatasculptor.workers.dev/",
    "link": "https://strzelceopolskie.naszemiasto.pl/gmina-wygrala-proces-o-dwa-miliony-nie-musi-placic-za-drogi-w-szczerym-polu/ar/c1p2-28697695",
    "title": "Gmina wygrała proces o dwa miliony. Nie musi płacić za drogi w szczerym polu",
    "summary": "",
    "content": "",
    "published": "2026-02-05T12:56:29+00:00"
  },
  {
    "source": "https://wild-union-5400.thedatasculptor.workers.dev/",
    "link": "https://strzelceopolskie.naszemiasto.pl/od-czwartku-wielkie-obnizki-w-lidlu-tylko-do-wyczerpania-zapasow/ar/c1p2-28698291",
    "title": "Od czwartku wielkie obniżki w Lidlu. Tylko do wyczerpania zapasów",
    "summary": "",
    "content": "",
    "published": "2026-02-05T12:56:29+00:00",
    "id": "e7e72d860d1925570dfb70ab2b8ed87fc506a48a",
    "preselect": false
  },
  {
    "source": "https://wild-union-5400.thedatasculptor.workers.dev/",
    "link": "https://strzelceopolskie.naszemiasto.pl/charytatywny-festiwal-dmuchancow-dla-laury-rodzina-walczy-o-koszmarnie-drogi-lek-z-usa/ar/c1p2-28697757",
    "title": "NASZ PATRONAT Charytatywny Festiwal Dmuchańców dla Laury. Rodzina walczy o koszmarnie drogi lek z USA",
    "summary": "",
    "content": "",
    "published": "2026-02-05T12:56:29+00:00",
    "id": "118921cecab1be80997fecbf35f2850638242572",
    "preselect": false
  },
  {
    "source": "https://wild-union-5400.thedatasculptor.workers.dev/",
    "link": "https://motofakty.pl/jakie-nowe-auta-wybieraja-polacy-tak-kupujacy-zaczeli-2026-rok/ar/c4p2-28694511",
    "title": "Jakie nowe auta wybierają Polacy? Tak kupujący zaczęli 2026 rok",
    "summary": "",
    "content": "",
    "published": "2026-02-05T12:56:29+00:00",
    "id": "093dda6aa1f405e49cba9901dc099deda7c4d37c",
    "preselect": false
  },
  {
    "source": "https://wild-union-5400.thedatasculptor.workers.dev/",
    "link": "https://motofakty.pl/ktore-4-i-5-letnie-auta-sa-najmniej-awaryjne-ranking-awaryjnosci-aut-tuv-2026/ar/c4p2-28693835",
    "title": "Które 4- i 5-letnie auta są najmniej awaryjne? Ranking awaryjności aut TÜV 2026",
    "summary": "",
    "content": "",
    "published": "2026-02-05T12:56:29+00:00",
    "id": "3853cf9ef071f19b2bc307d27080a5d927683296",
    "preselect": false
  },
  {
    "source": "https://wild-union-5400.thedatasculptor.workers.dev/",
    "link": "https://strzelceopolskie.naszemiasto.pl/walentynki-2026-ile-polacy-zamierzaja-wydac-na-prezent/ar/c6p2-28695175",
    "title": "Walentynki 2026 - ile Polacy zamierzają wydać na prezent?",
    "summary": "",
    "content": "",
    "published": "2026-02-05T12:56:29+00:00",
    "id": "17fa406b760559d144edf4cdab84264118e87898",
    "preselect": false
  }
]