[
  {
    "source": "https://wild-union-5400.thedatasculptor.workers.dev/",
    "link": "https://strzelceopolskie.naszemiasto.pl/woj-opolskie-gdzie-sa-utrudnienia-w-ruchu-sprawdz-gdzie-sa-remonty-i-inne-zdarzenia-19-05-2026/ar/c1p1-21631769",
    "title": "Woj. opolskie - gdzie są utrudnienia w ruchu? Sprawdź, gdzie są remonty i inne zdarzenia 19.05.2026",
    "summary": "",
    "content": "",
    "published": "2026-05-19T19:48:27+00:00",
    "id": "7eb7d63db6cafcdb13d9b3feac09babc824cc69b",
    "preselect": true,
    "places_german": [
      "Oppeln"
    ]
  }
]